elastic_log_cli/__init__.py
elastic_log_cli/__main__.py
elastic_log_cli/_compat/__init__.py
elastic_log_cli/_compat/aws.py
elastic_log_cli/cli.py
elastic_log_cli/config.py
elastic_log_cli/exceptions.py
elastic_log_cli/kql/__init__.py
elastic_log_cli/kql/kql.grammar
elastic_log_cli/kql/parser.py
elastic_log_cli/py.typed
elastic_log_cli/search.py
elastic_log_cli/utils/__init__.py
elastic_log_cli/utils/backoff.py
elastic_log_cli-0.2.1.dist-info/entry_points.txt
elastic_log_cli-0.2.1.dist-info/LICENSE.txt
elastic_log_cli-0.2.1.dist-info/WHEEL
elastic_log_cli-0.2.1.dist-info/METADATA
elastic_log_cli-0.2.1.dist-info/RECORD
