Metadata-Version: 2.1
Name: elastic-log-cli
Version: 0.2.1
Summary: 
Home-page: https://github.com/jacksmith15/elastic-log-cli
Author: Jack Smith
Requires-Python: >=3.10,<4.0
Classifier: Programming Language :: Python :: 3
Classifier: Programming Language :: Python :: 3.10
Provides-Extra: aws
Requires-Dist: boto3 (>=1.24.46,<2.0.0); extra == "aws"
Requires-Dist: botocore (>=1.27.46,<2.0.0); extra == "aws"
Requires-Dist: click (>=8.0.4,<9.0.0)
Requires-Dist: lark (>=1.1.1,<2.0.0)
Requires-Dist: pydantic (>=1.9.0,<2.0.0)
Requires-Dist: requests (>=2.28.1,<3.0.0)
Project-URL: Repository, https://github.com/jacksmith15/elastic-log-cli
